Workbook

Sheet Read me
A1: BusinessIdea.io writing sheet
A3: 1. Open the Batch Prompts page, tap Copy on a batch and paste it into any writing tool. Fresh chat for every batch.
A4: 2. Copy the answer with the code block's own copy button.
A5: 3. Paste it into the Paste tab, column A, in the first empty cell. Paste nothing anywhere else.
A6: 4. Column B says OK, WRONG FIELD COUNT or NO END. Red rows: ask the tool to rewrite that idea, paste the new line below, and delete the red one.
A7: 5. Type next in the tool for the next subcategory (5 per batch). AI Studio: type all for all 50 at once. If it stops halfway, type continue.
A8: 6. In the Batches tab, write which account took the batch and set Status. Column G counts the OK ideas for that batch (50 = complete).
A9: 7. The Ideas tab fills itself with every OK row split into 31 columns. To upload: File > Download > CSV while the Ideas tab is open.
A11: Do not type in the Ideas tab or in columns B to D of the Paste tab: they are formulas.

Sheet Paste
A1: Paste rows here (column A only) | B1: Check | C1: Idea code | D1: Duplicate | F1: Summary
B2: =ARRAYFORMULA(IF(A2:A="",,IF((LEN(A2:A)-LEN(SUBSTITUTE(A2:A," | ","")))/3<>30,"WRONG FIELD COUNT",IF(RIGHT(TRIM(A2:A),3)<>"END","NO END","OK")))) | C2: =ARRAYFORMULA(IF(A2:A="",,IFERROR(REGEXEXTRACT(A2:A,"C[0-9]{3}-S[0-9]{2}-I[0-9]{2}"),"NO CODE"))) | D2: =ARRAYFORMULA(IF(C2:C="",,IF(COUNTIF(C2:C,C2:C)>1,"DUPLICATE",))) | F2: OK ideas | G2: =COUNTIF(B2:B,"OK")
F3: Rows with a problem | G3: =COUNTA(A2:A)-G2
F4: Duplicate codes | G4: =COUNTIF(D2:D,"DUPLICATE")
F5: Target | G5: 10000

Sheet Ideas
A1: code | B1: title | C1: slug | D1: hook | E1: summary | F1: what_it_is | G1: who_pays_you | H1: how_money_comes | I1: what_you_need | J1: step1 | K1: step2 | L1: step3 | M1: step4 | N1: step5 | O1: what_hurts | P1: verdict | Q1: faq1_q | R1: faq1_a | S1: faq2_q | T1: faq2_a | U1: faq3_q | V1: faq3_a | W1: validate_prompt | X1: investment_band | Y1: gender_fit | Z1: life_stage | AA1: place | AB1: work_mode | AC1: time_needed | AD1: skill_level | AE1: end_marker
A2: =ARRAYFORMULA(IFERROR(SPLIT(FILTER(Paste!A2:A,Paste!B2:B="OK")," | ",FALSE,FALSE)))

Sheet Batches
A1: Batch | B1: Category | C1: Category name | D1: Subcategories | E1: Account | F1: Status | G1: OK ideas (of 50) | H1: Notes
A2: B001 | B2: C001 | C2: Work From Home Business Ideas | D2: Home Cooked Meal Subscription, After School Online Tuition, Catalog Reselling From Home, Home Visit Beauty Service, Website and Blog Writing | F2: done | G2: =SUMPRODUCT((Paste!$B$2:$B$20000="OK")*REGEXMATCH(Paste!$C$2:$C$20000&"","^C001-S0[1-5]-I")) | H2: C001 S01 to S05 already in the repo
A3: B002 | B3: C001 | C3: Work From Home Business Ideas | D3: Small Shop Page Handling, Homemade Candle and Soap, Remote Admin Support, Printable and Digital File Selling, Live Online Workshop | F3: todo | G3: =SUMPRODUCT((Paste!$B$2:$B$20000="OK")*REGEXMATCH(Paste!$C$2:$C$20000&"","^C001-S(0[6-9]|10)-I"))
A4: B003 | B4: C002 | C4: Side Hustle Business Ideas | D4: Evening Tuition Side Work, Weekend Food Stall, Social App Product Reselling, Spare Time Design Service, Society Service Side Work | F4: todo | G4: =SUMPRODUCT((Paste!$B$2:$B$20000="OK")*REGEXMATCH(Paste!$C$2:$C$20000&"","^C002-S0[1-5]-I"))
A5: B004 | B5: C002 | C5: Side Hustle Business Ideas | D5: Festival Season Extra Work, Delivery Shift Side Work, Spare Time Content Service, Home Baking Order Side Work, Local Shop Support Side Work | F5: todo | G5: =SUMPRODUCT((Paste!$B$2:$B$20000="OK")*REGEXMATCH(Paste!$C$2:$C$20000&"","^C002-S(0[6-9]|10)-I"))
A6: B005 | B6: C003 | C6: Part Time Business Ideas | D6: Morning Meal Round, After Office Coaching Batch, Weekend Market Stall, Part Time Shop Accounts Help, Evening Hobby Batch | F6: todo | G6: =SUMPRODUCT((Paste!$B$2:$B$20000="OK")*REGEXMATCH(Paste!$C$2:$C$20000&"","^C003-S0[1-5]-I"))
A7: B006 | B7: C003 | C7: Part Time Business Ideas | D7: Part Time Event Photography, Weekend Catering Order, Part Time Online Selling, School Gate Help Service, Part Time Repair Visit | F7: todo | G7: =SUMPRODUCT((Paste!$B$2:$B$20000="OK")*REGEXMATCH(Paste!$C$2:$C$20000&"","^C003-S(0[6-9]|10)-I"))
A8: B007 | B8: C004 | C8: Online Business Ideas | D8: Own Brand Online Store, Marketplace Seller Account, Online Course Selling, Niche Information Website, Remote Client Service | F8: todo | G8: =SUMPRODUCT((Paste!$B$2:$B$20000="OK")*REGEXMATCH(Paste!$C$2:$C$20000&"","^C004-S0[1-5]-I"))
A9: B008 | B9: C004 | C9: Online Business Ideas | D9: WhatsApp and Instagram Shop, Print on Demand Product, Paid Online Community, Digital Download Shop, Online Booking Service | F9: todo | G9: =SUMPRODUCT((Paste!$B$2:$B$20000="OK")*REGEXMATCH(Paste!$C$2:$C$20000&"","^C004-S(0[6-9]|10)-I"))
A10: B009 | B10: C005 | C10: Home Based Business Ideas | D10: Home Tailoring Work, Home Pickle and Papad, Home Beauty Studio, Home Tuition Batch, Home Garment Making | F10: todo | G10: =SUMPRODUCT((Paste!$B$2:$B$20000="OK")*REGEXMATCH(Paste!$C$2:$C$20000&"","^C005-S0[1-5]-I"))
A11: B010 | B11: C005 | C11: Home Based Business Ideas | D11: Home Packed Food Brand, Home Child Care, Home Jewellery Making, Home Computer Class, Home Wash and Iron | F11: todo | G11: =SUMPRODUCT((Paste!$B$2:$B$20000="OK")*REGEXMATCH(Paste!$C$2:$C$20000&"","^C005-S(0[6-9]|10)-I"))
A12: B011 | B12: C006 | C12: Women Friendly Business Ideas | D12: Women Led Home Food, Women Led Beauty Work, Women Led Stitching Work, Homemaker Reselling, Women Led Teaching From Home | F12: todo | G12: =SUMPRODUCT((Paste!$B$2:$B$20000="OK")*REGEXMATCH(Paste!$C$2:$C$20000&"","^C006-S0[1-5]-I"))
A13: B012 | B13: C006 | C13: Women Friendly Business Ideas | D13: Women Led Craft Brand, Women Group Catering, Women Wellness Service, Women Led Kids Class, Homemaker Online Service | F13: todo | G13: =SUMPRODUCT((Paste!$B$2:$B$20000="OK")*REGEXMATCH(Paste!$C$2:$C$20000&"","^C006-S(0[6-9]|10)-I"))
A14: B013 | B14: C007 | C14: Student Business Ideas | D14: Study Notes Selling, Student Freelance Skill, College Event Coverage, Student Social Selling, Peer Tutoring by Students | F14: todo | G14: =SUMPRODUCT((Paste!$B$2:$B$20000="OK")*REGEXMATCH(Paste!$C$2:$C$20000&"","^C007-S0[1-5]-I"))
A15: B014 | B15: C007 | C15: Student Business Ideas | D15: Campus Snack Selling, Student Creator Channel, College Fest Stall, Student Page Handling, Campus Print and Design Service | F15: todo | G15: =SUMPRODUCT((Paste!$B$2:$B$20000="OK")*REGEXMATCH(Paste!$C$2:$C$20000&"","^C007-S(0[6-9]|10)-I"))
A16: B015 | B16: C008 | C16: Senior Citizen Business Ideas | D16: Retired Teacher Class, Experience Based Advice Service, Senior Home Kitchen Brand, Retired Society Service, Hobby Teaching by Seniors | F16: todo | G16: =SUMPRODUCT((Paste!$B$2:$B$20000="OK")*REGEXMATCH(Paste!$C$2:$C$20000&"","^C008-S0[1-5]-I"))
A17: B016 | B17: C008 | C17: Senior Citizen Business Ideas | D17: Senior Plant Nursery, Retired Accounts Help, Senior Writing and Editing, Senior Led Local Walks, Career Mentoring by Seniors | F17: todo | G17: =SUMPRODUCT((Paste!$B$2:$B$20000="OK")*REGEXMATCH(Paste!$C$2:$C$20000&"","^C008-S(0[6-9]|10)-I"))
A18: B017 | B18: C009 | C18: Village and Small Town Business Ideas | D18: Village Daily Needs Shop, Small Town Tuition Centre, Village Milk Collection, Small Town Beauty Parlour, Farm Input Retail Shop | F18: done | G18: =SUMPRODUCT((Paste!$B$2:$B$20000="OK")*REGEXMATCH(Paste!$C$2:$C$20000&"","^C009-S0[1-5]-I")) | H18: C009 already in the repo
A19: B018 | B19: C009 | C19: Village and Small Town Business Ideas | D19: Village Spice and Flour Mill, Small Town Phone Repair, Village Function Catering, Town Two Wheeler Workshop, Small Town Passenger Transport | F19: done | G19: =SUMPRODUCT((Paste!$B$2:$B$20000="OK")*REGEXMATCH(Paste!$C$2:$C$20000&"","^C009-S(0[6-9]|10)-I")) | H19: C009 already in the repo
A20: B019 | B20: C010 | C20: Local Service Business Ideas | D20: Neighbourhood Home Help, Building Upkeep Service, Local Parcel Movement, Doorstep Grooming Service, Local Print and Copy Shop | F20: todo | G20: =SUMPRODUCT((Paste!$B$2:$B$20000="OK")*REGEXMATCH(Paste!$C$2:$C$20000&"","^C010-S0[1-5]-I"))
A21: B020 | B21: C010 | C21: Local Service Business Ideas | D21: Nearby Appliance Care, Local Tutor Network, Area Meal Delivery Kitchen, Local Function Support, Market Day Service | F21: todo | G21: =SUMPRODUCT((Paste!$B$2:$B$20000="OK")*REGEXMATCH(Paste!$C$2:$C$20000&"","^C010-S(0[6-9]|10)-I"))
A22: B021 | B22: C011 | C22: Skill Based Business Ideas | D22: Trade Skill Site Work, Paid Skill Teaching, Maker Skill Product, Repair Skill Visit, Beauty Skill Booking | F22: todo | G22: =SUMPRODUCT((Paste!$B$2:$B$20000="OK")*REGEXMATCH(Paste!$C$2:$C$20000&"","^C011-S0[1-5]-I"))
A23: B022 | B23: C011 | C23: Skill Based Business Ideas | D23: Cooking Skill Order, Digital Skill Client Work, Language Skill Class, Fitness Skill Session, Craft Skill Product | F23: todo | G23: =SUMPRODUCT((Paste!$B$2:$B$20000="OK")*REGEXMATCH(Paste!$C$2:$C$20000&"","^C011-S(0[6-9]|10)-I"))
A24: B023 | B24: C012 | C24: Freelance Business Ideas | D24: Freelance Article Client, Freelance Design Project, Freelance Video Edit, Freelance Website Project, Freelance Marketing Retainer | F24: todo | G24: =SUMPRODUCT((Paste!$B$2:$B$20000="OK")*REGEXMATCH(Paste!$C$2:$C$20000&"","^C012-S0[1-5]-I"))
A25: B024 | B25: C012 | C25: Freelance Business Ideas | D25: Freelance Translation Work, Freelance Voice Over, Freelance Coding Project, Freelance Remote Support, Freelance Advice Call | F25: todo | G25: =SUMPRODUCT((Paste!$B$2:$B$20000="OK")*REGEXMATCH(Paste!$C$2:$C$20000&"","^C012-S(0[6-9]|10)-I"))
A26: B025 | B26: C013 | C26: Reselling Business Ideas | D26: Fashion Catalog Reselling, Beauty Item Reselling, Home Utility Reselling, Kids Item Reselling, WhatsApp Group Reselling | F26: todo | G26: =SUMPRODUCT((Paste!$B$2:$B$20000="OK")*REGEXMATCH(Paste!$C$2:$C$20000&"","^C013-S0[1-5]-I"))
A27: B026 | B27: C013 | C27: Reselling Business Ideas | D27: Closet and Thrift Reselling, Wholesale Lot to Local Sale, Festival Goods Reselling, Hostel Needs Reselling, Daily Needs Basket Reselling | F27: todo | G27: =SUMPRODUCT((Paste!$B$2:$B$20000="OK")*REGEXMATCH(Paste!$C$2:$C$20000&"","^C013-S(0[6-9]|10)-I"))
A28: B027 | B28: C014 | C28: Childcare and Parenting Support Business Ideas | D28: Home Daycare Group, After School Child Watch, Baby Care Visit Service, Parent Child Activity Batch, Kids Birthday Support | F28: todo | G28: =SUMPRODUCT((Paste!$B$2:$B$20000="OK")*REGEXMATCH(Paste!$C$2:$C$20000&"","^C014-S0[1-5]-I"))
A29: B028 | B29: C014 | C29: Childcare and Parenting Support Business Ideas | D29: School Van Route, Tuition With Child Watch, New Mother Home Support, Kids Hobby Group, Parent Learning Kit | F29: todo | G29: =SUMPRODUCT((Paste!$B$2:$B$20000="OK")*REGEXMATCH(Paste!$C$2:$C$20000&"","^C014-S(0[6-9]|10)-I"))
A30: B029 | B30: C015 | C30: Printing and Signage Business Ideas | D30: Copy and Print Shop, Wedding Card Print, Banner and Flex Print, Custom Apparel Print, Label and Sticker Print | F30: todo | G30: =SUMPRODUCT((Paste!$B$2:$B$20000="OK")*REGEXMATCH(Paste!$C$2:$C$20000&"","^C015-S0[1-5]-I"))
A31: B030 | B31: C015 | C31: Printing and Signage Business Ideas | D31: Name Plate and Stamp Shop, Photo Book Print, School Print Job, Vehicle Sticker and Graphics, Pack Print for Small Brands | F31: todo | G31: =SUMPRODUCT((Paste!$B$2:$B$20000="OK")*REGEXMATCH(Paste!$C$2:$C$20000&"","^C015-S(0[6-9]|10)-I"))
A32: B031 | B32: C016 | C32: Food Business Ideas | D32: Daily Dabba Supply, Namkeen Making and Packing, Regional Thali Meal, Office Lunch Contract, Festival Food Order | F32: todo | G32: =SUMPRODUCT((Paste!$B$2:$B$20000="OK")*REGEXMATCH(Paste!$C$2:$C$20000&"","^C016-S0[1-5]-I"))
A33: B032 | B33: C016 | C33: Food Business Ideas | D33: Special Diet Meal Kitchen, Night Eatery Food, House Party Food Order, Travel Stop Food, Hostel and Canteen Meal | F33: todo | G33: =SUMPRODUCT((Paste!$B$2:$B$20000="OK")*REGEXMATCH(Paste!$C$2:$C$20000&"","^C016-S(0[6-9]|10)-I"))
A34: B033 | B34: C017 | C34: Home Kitchen Food Business Ideas | D34: Homemade Pickle Brand, Papad Making at Home, Home Spice Mix Brand, Homemade Sweet Box, Batter and Ready Mix | F34: todo | G34: =SUMPRODUCT((Paste!$B$2:$B$20000="OK")*REGEXMATCH(Paste!$C$2:$C$20000&"","^C017-S0[1-5]-I"))
A35: B034 | B35: C017 | C35: Home Kitchen Food Business Ideas | D35: Home Chocolate Making, Dry Snack Packing at Home, Chutney and Sauce Making, Festival Food Hamper, Single Dish Home Kitchen | F35: todo | G35: =SUMPRODUCT((Paste!$B$2:$B$20000="OK")*REGEXMATCH(Paste!$C$2:$C$20000&"","^C017-S(0[6-9]|10)-I"))
A36: B035 | B36: C018 | C36: Street Food Business Ideas | D36: Chaat and Snack Cart, Momos and Dumpling Stall, Roll and Wrap Stall, South Indian Tiffin Stall, Juice and Shake Cart | F36: todo | G36: =SUMPRODUCT((Paste!$B$2:$B$20000="OK")*REGEXMATCH(Paste!$C$2:$C$20000&"","^C018-S0[1-5]-I"))
A37: B036 | B37: C018 | C37: Street Food Business Ideas | D37: Tea Stall, Indo Chinese Stall, Evening Fry Snack Stall, Egg and Non Veg Street Stall, Seasonal Street Snack | F37: todo | G37: =SUMPRODUCT((Paste!$B$2:$B$20000="OK")*REGEXMATCH(Paste!$C$2:$C$20000&"","^C018-S(0[6-9]|10)-I"))
A38: B037 | B38: C019 | C38: Bakery and Confectionery Business Ideas | D38: Custom Celebration Cake, Bread and Bun Bakery, Cookie and Biscuit Batch, Eggless Bake House, Dessert Box Bakery | F38: todo | G38: =SUMPRODUCT((Paste!$B$2:$B$20000="OK")*REGEXMATCH(Paste!$C$2:$C$20000&"","^C019-S0[1-5]-I"))
A39: B038 | B39: C019 | C39: Bakery and Confectionery Business Ideas | D39: Bakery Supply to Cafes, Wedding Dessert Table, Millet and Healthy Bake, Shop Counter Bakery, Festival Gift Bake | F39: todo | G39: =SUMPRODUCT((Paste!$B$2:$B$20000="OK")*REGEXMATCH(Paste!$C$2:$C$20000&"","^C019-S(0[6-9]|10)-I"))
A40: B039 | B40: C020 | C40: Catering Business Ideas | D40: Wedding Meal Catering, Small House Party Catering, Office Gathering Catering, Religious Function Meal, Live Food Counter | F40: todo | G40: =SUMPRODUCT((Paste!$B$2:$B$20000="OK")*REGEXMATCH(Paste!$C$2:$C$20000&"","^C020-S0[1-5]-I"))
A41: B040 | B41: C020 | C41: Catering Business Ideas | D41: Pure Vegetarian Catering, Regional Cuisine Catering, Reception Snack Catering, Outdoor Function Meal, Bulk Meal Contract | F41: todo | G41: =SUMPRODUCT((Paste!$B$2:$B$20000="OK")*REGEXMATCH(Paste!$C$2:$C$20000&"","^C020-S(0[6-9]|10)-I"))
A42: B041 | B42: C021 | C42: Cloud Kitchen Business Ideas | D42: Single Cuisine Delivery Kitchen, Biryani Delivery Kitchen, Grain Bowl Delivery Kitchen, Breakfast Delivery Kitchen, Late Night Delivery Kitchen | F42: todo | G42: =SUMPRODUCT((Paste!$B$2:$B$20000="OK")*REGEXMATCH(Paste!$C$2:$C$20000&"","^C021-S0[1-5]-I"))
A43: B042 | B43: C021 | C43: Cloud Kitchen Business Ideas | D43: Combo Plate Delivery Kitchen, Thali Delivery Kitchen, Dessert Delivery Kitchen, Shared Kitchen Multi Brand, Society Area Delivery Kitchen | F43: todo | G43: =SUMPRODUCT((Paste!$B$2:$B$20000="OK")*REGEXMATCH(Paste!$C$2:$C$20000&"","^C021-S(0[6-9]|10)-I"))
A44: B043 | B44: C022 | C44: Packaged Snack Business Ideas | D44: Classic Namkeen Brand, Roasted Nut and Seed Pack, Millet Snack Brand, Fried and Baked Chip, School Snack Pack | F44: todo | G44: =SUMPRODUCT((Paste!$B$2:$B$20000="OK")*REGEXMATCH(Paste!$C$2:$C$20000&"","^C022-S0[1-5]-I"))
A45: B044 | B45: C022 | C45: Packaged Snack Business Ideas | D45: Office Pantry Snack Supply, Regional Dry Snack Brand, Protein Munch Pack, Festival Snack Gift Pack, Savoury Mixture Brand | F45: todo | G45: =SUMPRODUCT((Paste!$B$2:$B$20000="OK")*REGEXMATCH(Paste!$C$2:$C$20000&"","^C022-S(0[6-9]|10)-I"))
A46: B045 | B46: C023 | C46: Beverage Stall and Drink Brand Business Ideas | D46: Fresh Juice and Shake Bar, Tea Stall and Chai Brand, Coffee Counter, Traditional Indian Cool Drink, Packaged Health Drink Mix | F46: todo | G46: =SUMPRODUCT((Paste!$B$2:$B$20000="OK")*REGEXMATCH(Paste!$C$2:$C$20000&"","^C023-S0[1-5]-I"))
A47: B046 | B47: C023 | C47: Beverage Stall and Drink Brand Business Ideas | D47: Office Beverage Supply, Summer Drink Cart, Party Mocktail Service, Regional Drink Brand, Drink Base and Syrup Supply | F47: todo | G47: =SUMPRODUCT((Paste!$B$2:$B$20000="OK")*REGEXMATCH(Paste!$C$2:$C$20000&"","^C023-S(0[6-9]|10)-I"))
A48: B047 | B48: C024 | C48: Sweet Shop and Mithai Business Ideas | D48: Neighbourhood Mithai Shop, Festival Sweet Order, Regional Sweet Speciality, Dry Fruit Sweet Box, Milk Based Sweet Making | F48: todo | G48: =SUMPRODUCT((Paste!$B$2:$B$20000="OK")*REGEXMATCH(Paste!$C$2:$C$20000&"","^C024-S0[1-5]-I"))
A49: B048 | B49: C024 | C49: Sweet Shop and Mithai Business Ideas | D49: Low Sugar Sweet Option, Sweet Gift Hamper, Wedding Sweet Box, Sweet and Snack Shop, Seasonal Sweet Calendar | F49: todo | G49: =SUMPRODUCT((Paste!$B$2:$B$20000="OK")*REGEXMATCH(Paste!$C$2:$C$20000&"","^C024-S(0[6-9]|10)-I"))
A50: B049 | B50: C025 | C50: Restaurant and Eatery Business Ideas | D50: Small Family Eatery, Quick Service Counter, Dhaba Style Meal Stop, South Indian Meals Hotel, North Indian Thali House | F50: todo | G50: =SUMPRODUCT((Paste!$B$2:$B$20000="OK")*REGEXMATCH(Paste!$C$2:$C$20000&"","^C025-S0[1-5]-I"))
A51: B050 | B51: C025 | C51: Restaurant and Eatery Business Ideas | D51: Casual Cafe, Pure Veg Eating House, Non Veg Speciality Eatery, Highway Meal Stop, Food Court Stall | F51: todo | G51: =SUMPRODUCT((Paste!$B$2:$B$20000="OK")*REGEXMATCH(Paste!$C$2:$C$20000&"","^C025-S(0[6-9]|10)-I"))
A52: B051 | B52: C026 | C52: Regional Specialty Food Business Ideas | D52: South Indian Food Brand, Gujarati Thali Food, Bengali Home Food Order, Punjabi Meal Joint, Kerala Meal and Snack | F52: todo | G52: =SUMPRODUCT((Paste!$B$2:$B$20000="OK")*REGEXMATCH(Paste!$C$2:$C$20000&"","^C026-S0[1-5]-I"))
A53: B052 | B53: C026 | C53: Regional Specialty Food Business Ideas | D53: Maharashtrian Food Speciality, Hyderabadi Food Brand, North East Food Kitchen, Coastal Fish Meal, Regional Street Snack Brand | F53: todo | G53: =SUMPRODUCT((Paste!$B$2:$B$20000="OK")*REGEXMATCH(Paste!$C$2:$C$20000&"","^C026-S(0[6-9]|10)-I"))
A54: B053 | B54: C027 | C54: Beauty Business Ideas | D54: Skin Facial Service, Hair Care Service, Bridal Makeup Artist, Mehendi Design Service, Nail Studio Service | F54: todo | G54: =SUMPRODUCT((Paste!$B$2:$B$20000="OK")*REGEXMATCH(Paste!$C$2:$C$20000&"","^C027-S0[1-5]-I"))
A55: B054 | B55: C027 | C55: Beauty Business Ideas | D55: Basic Salon Grooming, Beauty at Client Home, Beauty Product Resale, Makeup Skill Class, Party Makeup Booking | F55: todo | G55: =SUMPRODUCT((Paste!$B$2:$B$20000="OK")*REGEXMATCH(Paste!$C$2:$C$20000&"","^C027-S(0[6-9]|10)-I"))
A56: B055 | B56: C028 | C56: Salon and Grooming Business Ideas | D56: Women Beauty Parlour, Men Hair Salon, Unisex Local Salon, Kids Haircut Chair, Classic Barber Shop | F56: todo | G56: =SUMPRODUCT((Paste!$B$2:$B$20000="OK")*REGEXMATCH(Paste!$C$2:$C$20000&"","^C028-S0[1-5]-I"))
A57: B056 | B57: C028 | C57: Salon and Grooming Business Ideas | D57: Skin and Body Care Room, Salon Studio at Home, Salon Retail Shelf, Grooming Membership Plan, Salon Assistant Training | F57: todo | G57: =SUMPRODUCT((Paste!$B$2:$B$20000="OK")*REGEXMATCH(Paste!$C$2:$C$20000&"","^C028-S(0[6-9]|10)-I"))
A58: B057 | B58: C029 | C58: Bridal and Wedding Beauty Business Ideas | D58: Full Bridal Makeup Booking, Bridal Mehendi Team, Family Function Makeup, Groom Wedding Grooming, Outstation Wedding Beauty | F58: todo | G58: =SUMPRODUCT((Paste!$B$2:$B$20000="OK")*REGEXMATCH(Paste!$C$2:$C$20000&"","^C029-S0[1-5]-I"))
A59: B058 | B59: C029 | C59: Bridal and Wedding Beauty Business Ideas | D59: Pre Wedding Skin Care, Wedding Hair Draping, Bridesmaid Makeup Set, Makeup Trial Studio, Guest and Festive Makeup | F59: todo | G59: =SUMPRODUCT((Paste!$B$2:$B$20000="OK")*REGEXMATCH(Paste!$C$2:$C$20000&"","^C029-S(0[6-9]|10)-I"))
A60: B059 | B60: C030 | C60: Fashion and Apparel Business Ideas | D60: Ethnic Wear for Women, Daily Western Wear Selling, Kids Wear Label, Men Casual Wear Selling, Saree Selling | F60: todo | G60: =SUMPRODUCT((Paste!$B$2:$B$20000="OK")*REGEXMATCH(Paste!$C$2:$C$20000&"","^C030-S0[1-5]-I"))
A61: B060 | B61: C030 | C61: Fashion and Apparel Business Ideas | D61: Inclusive Size Clothing, Campus Wear Label, Workwear and Uniform Supply, Seasonal Clothing Drop, Preowned Clothing Trade | F61: todo | G61: =SUMPRODUCT((Paste!$B$2:$B$20000="OK")*REGEXMATCH(Paste!$C$2:$C$20000&"","^C030-S(0[6-9]|10)-I"))
A62: B061 | B62: C031 | C62: Tailoring and Boutique Business Ideas | D62: Ladies Tailoring Shop, Blouse and Ethnic Stitching, Alteration Desk, Small Designer Boutique, Men Formal Stitching | F62: todo | G62: =SUMPRODUCT((Paste!$B$2:$B$20000="OK")*REGEXMATCH(Paste!$C$2:$C$20000&"","^C031-S0[1-5]-I"))
A63: B062 | B63: C031 | C63: Tailoring and Boutique Business Ideas | D63: Children Dress Stitching, Home Visiting Tailor, Embroidery Work Add On, Outfit Hire Boutique, Bulk Stitching Order | F63: todo | G63: =SUMPRODUCT((Paste!$B$2:$B$20000="OK")*REGEXMATCH(Paste!$C$2:$C$20000&"","^C031-S(0[6-9]|10)-I"))
A64: B063 | B64: C032 | C64: Jewellery and Accessories Business Ideas | D64: Fashion Jewellery Selling, Handmade Jewellery Bench, Silver Ornament Shop, Bridal Jewellery Set, Daily Wear Accessory | F64: todo | G64: =SUMPRODUCT((Paste!$B$2:$B$20000="OK")*REGEXMATCH(Paste!$C$2:$C$20000&"","^C032-S0[1-5]-I"))
A65: B064 | B65: C032 | C65: Jewellery and Accessories Business Ideas | D65: Men Accessory Counter, Temple Jewellery Line, Name and Custom Jewel, Home Based Jewel Order, Boutique Counter Accessory | F65: todo | G65: =SUMPRODUCT((Paste!$B$2:$B$20000="OK")*REGEXMATCH(Paste!$C$2:$C$20000&"","^C032-S(0[6-9]|10)-I"))
A66: B065 | B66: C033 | C66: Footwear and Bag Business Ideas | D66: Women Footwear Shop, School Shoe Supply, Men Daily Shoe Shop, Handbag Selling, Travel Bag Shop | F66: todo | G66: =SUMPRODUCT((Paste!$B$2:$B$20000="OK")*REGEXMATCH(Paste!$C$2:$C$20000&"","^C033-S0[1-5]-I"))
A67: B066 | B67: C033 | C67: Footwear and Bag Business Ideas | D67: Ethnic Footwear Line, Shoe Repair Desk, Children Footwear Shop, Office Bag Selling, Footwear Selling Online | F67: todo | G67: =SUMPRODUCT((Paste!$B$2:$B$20000="OK")*REGEXMATCH(Paste!$C$2:$C$20000&"","^C033-S(0[6-9]|10)-I"))
A68: B067 | B68: C034 | C68: Handmade Product Business Ideas | D68: Scented Candle Studio, Cold Process Soap Studio, Resin Gift Studio, Wall Hanging Craft, Handmade Paper Gift | F68: todo | G68: =SUMPRODUCT((Paste!$B$2:$B$20000="OK")*REGEXMATCH(Paste!$C$2:$C$20000&"","^C034-S0[1-5]-I"))
A69: B068 | B69: C034 | C69: Handmade Product Business Ideas | D69: Clay and Pottery Studio, Cloth Doll and Soft Toy, Dried Flower Craft, Custom Commission Craft, Craft Market Selling | F69: todo | G69: =SUMPRODUCT((Paste!$B$2:$B$20000="OK")*REGEXMATCH(Paste!$C$2:$C$20000&"","^C034-S(0[6-9]|10)-I"))
A70: B069 | B70: C035 | C70: Personal Care Product Business Ideas | D70: Herbal Hair Oil Brand, Simple Skin Product Brand, Incense Stick Making, Lip Balm and Salve Making, Baby Care Herbal Line | F70: todo | G70: =SUMPRODUCT((Paste!$B$2:$B$20000="OK")*REGEXMATCH(Paste!$C$2:$C$20000&"","^C035-S0[1-5]-I"))
A71: B070 | B71: C035 | C71: Personal Care Product Business Ideas | D71: Men Grooming Product Line, Bath Product Making, Herbal Face Pack Mix, Salon Use Product Supply, Personal Care Gift Kit | F71: todo | G71: =SUMPRODUCT((Paste!$B$2:$B$20000="OK")*REGEXMATCH(Paste!$C$2:$C$20000&"","^C035-S(0[6-9]|10)-I"))
A72: B071 | B72: C036 | C72: Home Textile Business Ideas | D72: Bed Linen Selling, Curtain Making, Cushion Cover Making, Quilt and Blanket Making, Kitchen Textile Making | F72: todo | G72: =SUMPRODUCT((Paste!$B$2:$B$20000="OK")*REGEXMATCH(Paste!$C$2:$C$20000&"","^C036-S0[1-5]-I"))
A73: B072 | B73: C036 | C73: Home Textile Business Ideas | D73: Baby Bedding Making, Named Textile Gift, Handloom Fabric Selling, Stitching Cloth Supply, Made to Order Home Linen | F73: todo | G73: =SUMPRODUCT((Paste!$B$2:$B$20000="OK")*REGEXMATCH(Paste!$C$2:$C$20000&"","^C036-S(0[6-9]|10)-I"))
A74: B073 | B74: C037 | C74: Education Business Ideas | D74: School Subject Class, College Subject Support, Spoken English Batch, Short Skill Course, Early Learner Class | F74: todo | G74: =SUMPRODUCT((Paste!$B$2:$B$20000="OK")*REGEXMATCH(Paste!$C$2:$C$20000&"","^C037-S0[1-5]-I"))
A75: B074 | B75: C037 | C75: Education Business Ideas | D75: Adult Learning Batch, Study Guide Selling, Course and College Guidance, Catch Up Learning Batch, Small Group Class | F75: todo | G75: =SUMPRODUCT((Paste!$B$2:$B$20000="OK")*REGEXMATCH(Paste!$C$2:$C$20000&"","^C037-S(0[6-9]|10)-I"))
A76: B075 | B76: C038 | C76: Tuition and Coaching Business Ideas | D76: Board Exam Tuition, Primary Grade Tuition, Maths Tuition Batch, Science Tuition Batch, Commerce Tuition Batch | F76: todo | G76: =SUMPRODUCT((Paste!$B$2:$B$20000="OK")*REGEXMATCH(Paste!$C$2:$C$20000&"","^C038-S0[1-5]-I"))
A77: B076 | B77: C038 | C77: Tuition and Coaching Business Ideas | D77: Tutor at Student Home, Local Tuition Centre, Live Online Tuition, Weekly Test Batch, Holiday Revision Batch | F77: todo | G77: =SUMPRODUCT((Paste!$B$2:$B$20000="OK")*REGEXMATCH(Paste!$C$2:$C$20000&"","^C038-S(0[6-9]|10)-I"))
A78: B077 | B78: C039 | C78: Competitive Exam Coaching Business Ideas | D78: SSC Coaching Batch, Bank Exam Coaching, Railway Exam Coaching, Medical Entrance Support, Engineering Entrance Support | F78: todo | G78: =SUMPRODUCT((Paste!$B$2:$B$20000="OK")*REGEXMATCH(Paste!$C$2:$C$20000&"","^C039-S0[1-5]-I"))
A79: B078 | B79: C039 | C79: Competitive Exam Coaching Business Ideas | D79: State Service Exam Coaching, Defence Exam Coaching, Teacher Eligibility Coaching, University Entrance Coaching, Daily Current Affairs Batch | F79: todo | G79: =SUMPRODUCT((Paste!$B$2:$B$20000="OK")*REGEXMATCH(Paste!$C$2:$C$20000&"","^C039-S(0[6-9]|10)-I"))
A80: B079 | B80: C040 | C80: Language and Communication Training Business Ideas | D80: Spoken English Centre, Hindi for New Residents, Overseas English Test Prep, Workplace Speaking Class, Regional Language Class | F80: todo | G80: =SUMPRODUCT((Paste!$B$2:$B$20000="OK")*REGEXMATCH(Paste!$C$2:$C$20000&"","^C040-S0[1-5]-I"))
A81: B080 | B81: C040 | C81: Language and Communication Training Business Ideas | D81: Interview Practice Batch, Children Spoken English, Fluency Practice Group, Office Language Batch, Online Speaking Partner | F81: todo | G81: =SUMPRODUCT((Paste!$B$2:$B$20000="OK")*REGEXMATCH(Paste!$C$2:$C$20000&"","^C040-S(0[6-9]|10)-I"))
A82: B081 | B82: C041 | C82: Skill Training and Vocational Business Ideas | D82: Stitching Training Batch, Beauty Trade Training, Phone Repair Training, Basic Computer Training, Electric Trade Helper Training | F82: todo | G82: =SUMPRODUCT((Paste!$B$2:$B$20000="OK")*REGEXMATCH(Paste!$C$2:$C$20000&"","^C041-S0[1-5]-I"))
A83: B082 | B83: C041 | C83: Skill Training and Vocational Business Ideas | D83: Bakery Skill Class, Driving School, Appliance Repair Training, Fashion Cutting Course, Job Ready Soft Skill Batch | F83: todo | G83: =SUMPRODUCT((Paste!$B$2:$B$20000="OK")*REGEXMATCH(Paste!$C$2:$C$20000&"","^C041-S(0[6-9]|10)-I"))
A84: B083 | B84: C042 | C84: Kids Learning and Activity Business Ideas | D84: Playgroup and Preschool, After School Activity Hub, Mental Maths Class, Children Drawing Class, Children Dance Class | F84: todo | G84: =SUMPRODUCT((Paste!$B$2:$B$20000="OK")*REGEXMATCH(Paste!$C$2:$C$20000&"","^C042-S0[1-5]-I"))
A85: B084 | B85: C042 | C85: Kids Learning and Activity Business Ideas | D85: Early Reading Class, Children Coding Play, Drama and Story Class, Summer Activity Camp, Children Robotics Batch | F85: todo | G85: =SUMPRODUCT((Paste!$B$2:$B$20000="OK")*REGEXMATCH(Paste!$C$2:$C$20000&"","^C042-S(0[6-9]|10)-I"))
A86: B085 | B86: C043 | C86: Hobby and Creative Class Business Ideas | D86: Adult Art Batch, Instrument Learning Class, Singing Group Class, Dance Batch for Adults, Weekend Cooking Class | F86: todo | G86: =SUMPRODUCT((Paste!$B$2:$B$20000="OK")*REGEXMATCH(Paste!$C$2:$C$20000&"","^C043-S0[1-5]-I"))
A87: B086 | B87: C043 | C87: Hobby and Creative Class Business Ideas | D87: Craft Workshop Series, Photo Hobby Workshop, Mehendi Learning Batch, Home Baking Class, Lettering Art Class | F87: todo | G87: =SUMPRODUCT((Paste!$B$2:$B$20000="OK")*REGEXMATCH(Paste!$C$2:$C$20000&"","^C043-S(0[6-9]|10)-I"))
A88: B087 | B88: C044 | C88: Computer and Digital Skill Training Business Ideas | D88: Beginner Computer Centre, Accounts Software Class, Design Software Course, Video Edit Course, Beginner Coding Batch | F88: todo | G88: =SUMPRODUCT((Paste!$B$2:$B$20000="OK")*REGEXMATCH(Paste!$C$2:$C$20000&"","^C044-S0[1-5]-I"))
A89: B088 | B89: C044 | C89: Computer and Digital Skill Training Business Ideas | D89: Spreadsheet Skill Class, Marketing Skill Course, Certificate Computer Course, Children Computer Batch, Freelance Skill Course | F89: todo | G89: =SUMPRODUCT((Paste!$B$2:$B$20000="OK")*REGEXMATCH(Paste!$C$2:$C$20000&"","^C044-S(0[6-9]|10)-I"))
A90: B089 | B90: C045 | C90: Test Preparation and Study Support Business Ideas | D90: Doubt Solving Session, Homework Help Batch, Practice Test Centre, Chapter Notes Shop, Parent Update Tuition | F90: todo | G90: =SUMPRODUCT((Paste!$B$2:$B$20000="OK")*REGEXMATCH(Paste!$C$2:$C$20000&"","^C045-S0[1-5]-I"))
A91: B090 | B91: C045 | C91: Test Preparation and Study Support Business Ideas | D91: Weak Topic Repair Batch, Early Study Batch, Guided Study Room, Board Practical Prep, Scholarship Test Prep | F91: todo | G91: =SUMPRODUCT((Paste!$B$2:$B$20000="OK")*REGEXMATCH(Paste!$C$2:$C$20000&"","^C045-S(0[6-9]|10)-I"))
A92: B091 | B92: C046 | C92: Teacher Led Business Ideas | D92: Teacher Owned Tuition Brand, Recorded Class Selling, Teacher Worksheet Shop, Teacher Video Class, School Linked Tuition | F92: todo | G92: =SUMPRODUCT((Paste!$B$2:$B$20000="OK")*REGEXMATCH(Paste!$C$2:$C$20000&"","^C046-S0[1-5]-I"))
A93: B092 | B93: C046 | C93: Teacher Led Business Ideas | D93: Teacher Made Learning Kit, Holiday Class by Teachers, Subject Update for Students, Teacher Support to Schools, Two Language Teaching | F93: todo | G93: =SUMPRODUCT((Paste!$B$2:$B$20000="OK")*REGEXMATCH(Paste!$C$2:$C$20000&"","^C046-S(0[6-9]|10)-I"))
A94: B093 | B94: C047 | C94: Digital Marketing Business Ideas | D94: Local Search Visibility Service, Map Listing Management, Ad Account Handling for Shops, Social Posting Service, WhatsApp Broadcast Service | F94: todo | G94: =SUMPRODUCT((Paste!$B$2:$B$20000="OK")*REGEXMATCH(Paste!$C$2:$C$20000&"","^C047-S0[1-5]-I"))
A95: B094 | B95: C047 | C95: Digital Marketing Business Ideas | D95: Review and Reply Handling, Product Listing Improvement, Monthly Content Plan Service, Home Based Marketing Desk, Festival Campaign Creative | F95: todo | G95: =SUMPRODUCT((Paste!$B$2:$B$20000="OK")*REGEXMATCH(Paste!$C$2:$C$20000&"","^C047-S(0[6-9]|10)-I"))
A96: B095 | B96: C048 | C96: Content Creation Business Ideas | D96: Short Video Making Service, Article Production Service, Audio Show Production Help, Email Letter Writing Service, Product Photo Set Service | F96: todo | G96: =SUMPRODUCT((Paste!$B$2:$B$20000="OK")*REGEXMATCH(Paste!$C$2:$C$20000&"","^C048-S0[1-5]-I"))
A97: B096 | B97: C048 | C97: Content Creation Business Ideas | D97: Hindi and Regional Content, Lesson Content Making, Brand Story Piece, Local Page Content, Old Content Refresh Service | F97: todo | G97: =SUMPRODUCT((Paste!$B$2:$B$20000="OK")*REGEXMATCH(Paste!$C$2:$C$20000&"","^C048-S(0[6-9]|10)-I"))
A98: B097 | B98: C049 | C98: Social Media Service Business Ideas | D98: Clinic Page Handling, Shop Page Handling, Restaurant Reel Service, Channel Upload Support, Professional Profile Refresh | F98: todo | G98: =SUMPRODUCT((Paste!$B$2:$B$20000="OK")*REGEXMATCH(Paste!$C$2:$C$20000&"","^C049-S0[1-5]-I"))
A99: B098 | B99: C049 | C99: Social Media Service Business Ideas | D99: Festival Post Design Service, Creator Collab Support, Customer Group Care, Property Agent Page Service, Monthly Posting Plan | F99: todo | G99: =SUMPRODUCT((Paste!$B$2:$B$20000="OK")*REGEXMATCH(Paste!$C$2:$C$20000&"","^C049-S(0[6-9]|10)-I"))
A100: B099 | B100: C050 | C100: Graphic Design and Branding Business Ideas | D100: Logo and Brand Starter Kit, Social Creative Design, Menu Card Design, Pack Design for Makers, Wedding Paper Design | F100: todo | G100: =SUMPRODUCT((Paste!$B$2:$B$20000="OK")*REGEXMATCH(Paste!$C$2:$C$20000&"","^C050-S0[1-5]-I"))
...

Sheet Format check
A1: C000-S00-I01 | test title | END | B1: =SPLIT(A1," | ",FALSE,FALSE)
A3: This tab only proves the split formula works after upload. Leave it.
